reversebox
