Metadata-Version: 2.4
Name: ReverseBox
Version: 0.83.0
Summary: A set of functions useful in reverse engineering.
Home-page: https://github.com/bartlomiejduda/ReverseBox
Author: Bartlomiej Duda
Author-email: ikskoks@gmail.com
License: GPL-3.0-or-later
Keywords: ReverseBox,reverse engineering,RE,CRC,Hash,Encryption,Compression,Checksum,Python,image,decode,decoding,RGB,swizzle,swizzling,morton,twiddle,twiddling,texture,UYVY,YUY2,NV21,NV12,RGBA,RGBA8888,RGB565,RGBA8,BGR,grayscale,graphics,color,pixel,convert,converting,YUV,RAW,PSP,PS1,PS2,PS3,PS4,XBOX,X360,gamecube,dreamcast,BC,BC1,BC2,BC3,BC4,BC5,BC6,BC7,DXT1,DXT2,DXT3,PackBits,RLE,Macintosh,Jenkins,murmur,murmur3,one-at-a-time,additive,ASTC,ETC1,ETC2,DXT2,DXT4,EAC,BASISU,PVRTCI,UASTC,RGBM,RGBD
Classifier: Programming Language :: Python :: 3
Classifier: Programming Language :: Python :: 3.6
Classifier: Programming Language :: Python :: 3.7
Classifier: Programming Language :: Python :: 3.8
Classifier: Programming Language :: Python :: 3.9
Classifier: Programming Language :: Python :: 3.10
Classifier: Programming Language :: Python :: 3.11
Classifier: Programming Language :: Python :: 3.12
Classifier: Programming Language :: Python :: 3.13
Classifier: Development Status :: 4 - Beta
Classifier: Topic :: Software Development
Classifier: Topic :: System :: Archiving :: Compression
Classifier: Topic :: Security :: Cryptography
Classifier: Environment :: Console
Classifier: Intended Audience :: Developers
Classifier: Intended Audience :: Science/Research
Classifier: Operating System :: OS Independent
Classifier: Natural Language :: English
Requires-Python: >=3.6
License-File: LICENSE
Requires-Dist: lzokay
Requires-Dist: polib
Requires-Dist: crc
Requires-Dist: hashbase
Requires-Dist: pillow
Requires-Dist: mmh3
Requires-Dist: lz4
Requires-Dist: numpy
Dynamic: author
Dynamic: author-email
Dynamic: classifier
Dynamic: description
Dynamic: description-content-type
Dynamic: home-page
Dynamic: keywords
Dynamic: license
Dynamic: license-file
Dynamic: requires-dist
Dynamic: requires-python
Dynamic: summary
